dronefly/core/__init__.py
dronefly/core/clients/__init__.py
dronefly/core/clients/inat.py
dronefly/core/commands/__init__.py
dronefly/core/constants.py
dronefly/core/formatters/__init__.py
dronefly/core/formatters/constants.py
dronefly/core/formatters/generic.py
dronefly/core/menus/__init__.py
dronefly/core/menus/menu.py
dronefly/core/menus/source.py
dronefly/core/menus/taxon.py
dronefly/core/menus/taxon_list.py
dronefly/core/models/__init__.py
dronefly/core/models/config.py
dronefly/core/models/controlled_terms.py
dronefly/core/models/user.py
dronefly/core/parsers/__init__.py
dronefly/core/parsers/constants.py
dronefly/core/parsers/natural.py
dronefly/core/parsers/unixlike.py
dronefly/core/parsers/url.py
dronefly/core/query/__init__.py
dronefly/core/query/query.py
dronefly/core/utils/__init__.py
dronefly_core-0.4.0.dist-info/LICENSE
dronefly_core-0.4.0.dist-info/METADATA
dronefly_core-0.4.0.dist-info/WHEEL
dronefly_core-0.4.0.dist-info/RECORD
