Metadata-Version: 2.1
Name: dronefly-core
Version: 0.4.0
Summary: Core dronefly components
License: AGPL-3.0-or-later
Author: Ben Armstrong
Author-email: synrg@debian.org
Requires-Python: >=3.11,<3.13
Classifier: License :: OSI Approved :: GNU Affero General Public License v3 or later (AGPLv3+)
Classifier: Programming Language :: Python :: 3
Classifier: Programming Language :: Python :: 3.11
Classifier: Programming Language :: Python :: 3.12
Requires-Dist: dateparser (>=1.1.1,<2.0.0)
Requires-Dist: filelock (>=3.13.3,<4.0.0)
Requires-Dist: html2markdown (>=0.1.7,<0.2.0)
Requires-Dist: inflect (>=5.3.0,<6.0.0)
Requires-Dist: pyinaturalist (>=0.20.0,<0.21.0)
Requires-Dist: rich (>=13.4)
